Tranferencia_Calor/__init__.py
Tranferencia_Calor/exampleChemicals.py
Tranferencia_Calor/fluidos.py
Tranferencia_Calor/fucionesItercambiador.py
Tranferencia_Calor/funcionesItercambiador.py
Transferencia_Calor-0.1.3.dist-info/METADATA
Transferencia_Calor-0.1.3.dist-info/WHEEL
Transferencia_Calor-0.1.3.dist-info/top_level.txt
Transferencia_Calor-0.1.3.dist-info/RECORD
