Metadata-Version: 2.1
Name: Transferencia-Calor
Version: 0.1.3
Summary: Librería para realizar simulaciones de un intercambiador de calor de coraza y tubos. la versión actual tiene la función para el calculó de la MLDT unicamente
Home-page: https://www.linkedin.com/in/isaac-chavez-analisisdedatatos-bigdata-automatizacion/
Author: Isaac Josué Chávez Martínez & Heber Mercado Martínez
Author-email: isaacj.ch.m@gmail.com
License: MIT
Platform: UNKNOWN
Requires-Dist: pandas==1.5.2
Requires-Dist: thermo==0.3.0
